odoo/addons/connector_base_product/README.rst
odoo/addons/connector_base_product/__init__.py
odoo/addons/connector_base_product/__manifest__.py
odoo/addons/connector_base_product/i18n/ca.po
odoo/addons/connector_base_product/i18n/connector_base_product.pot
odoo/addons/connector_base_product/i18n/de.po
odoo/addons/connector_base_product/i18n/es.po
odoo/addons/connector_base_product/i18n/fr.po
odoo/addons/connector_base_product/i18n/hu.po
odoo/addons/connector_base_product/i18n/it.po
odoo/addons/connector_base_product/i18n/nl.po
odoo/addons/connector_base_product/i18n/pt_BR.po
odoo/addons/connector_base_product/i18n/sl.po
odoo/addons/connector_base_product/i18n/zh_CN.po
odoo/addons/connector_base_product/readme/CONTRIBUTORS.rst
odoo/addons/connector_base_product/readme/DESCRIPTION.rst
odoo/addons/connector_base_product/static/description/icon.png
odoo/addons/connector_base_product/static/description/index.html
odoo/addons/connector_base_product/views/product_view.xml
odoo14_addon_connector_base_product-14.0.1.0.1.dev4.dist-info/METADATA
odoo14_addon_connector_base_product-14.0.1.0.1.dev4.dist-info/WHEEL
odoo14_addon_connector_base_product-14.0.1.0.1.dev4.dist-info/top_level.txt
odoo14_addon_connector_base_product-14.0.1.0.1.dev4.dist-info/RECORD
